{"copyright": "All data copyright Toronto Transit Commission 2025.", "route": {"path": [{"point": [{"lon": "-79.3223", "lat": "43.77188"}, {"lon": "-79.32231", "lat": "43.77176"}, {"lon": "-79.32328", "lat": "43.77161"}, {"lon": "-79.32373", "lat": "43.77154"}, {"lon": "-79.32382", "lat": "43.77153"}, {"lon": "-79.32397", "lat": "43.77149"}, {"lon": "-79.32408", "lat": "43.77144"}, {"lon": "-79.3242099", "lat": "43.77138"}, {"lon": "-79.32425", "lat": "43.77135"}, {"lon": "-79.32462", "lat": "43.77105"}, {"lon": "-79.32471", "lat": "43.77097"}, {"lon": "-79.32482", "lat": "43.77091"}, {"lon": "-79.32494", "lat": "43.77086"}, {"lon": "-79.32505", "lat": "43.77084"}, {"lon": "-79.32513", "lat": "43.77084"}, {"lon": "-79.32518", "lat": "43.77084"}, {"lon": "-79.3260899", "lat": "43.77077"}, {"lon": "-79.32692", "lat": "43.7708"}, {"lon": "-79.32809", "lat": "43.77063"}, {"lon": "-79.32963", "lat": "43.77053"}, {"lon": "-79.3299", "lat": "43.7705"}, {"lon": "-79.33015", "lat": "43.77057"}, {"lon": "-79.33013", "lat": "43.77046"}, {"lon": "-79.33028", "lat": "43.77043"}, {"lon": "-79.33043", "lat": "43.77041"}, {"lon": "-79.33058", "lat": "43.7704"}, {"lon": "-79.33076", "lat": "43.77043"}, {"lon": "-79.33089", "lat": "43.77047"}, {"lon": "-79.33098", "lat": "43.77051"}, {"lon": "-79.3310599", "lat": "43.7705399"}, {"lon": "-79.33113", "lat": "43.7706"}, {"lon": "-79.33122", "lat": "43.77068"}, {"lon": "-79.33128", "lat": "43.77076"}, {"lon": "-79.33136", "lat": "43.77091"}, {"lon": "-79.33142", "lat": "43.77105"}, {"lon": "-79.33146", "lat": "43.77119"}, {"lon": "-79.33185", "lat": "43.77112"}, {"lon": "-79.33198", "lat": "43.77116"}, {"lon": "-79.33408", "lat": "43.77064"}, {"lon": "-79.3345", "lat": "43.77055"}, {"lon": "-79.33459", "lat": "43.7705399"}, {"lon": "-79.33469", "lat": "43.77056"}, {"lon": "-79.33477", "lat": "43.77061"}, {"lon": "-79.3349099", "lat": "43.77078"}, {"lon": "-79.33516", "lat": "43.77116"}, {"lon": "-79.33559", "lat": "43.77152"}, {"lon": "-79.33569", "lat": "43.77163"}, {"lon": "-79.33583", "lat": "43.77194"}, {"lon": "-79.33622", "lat": "43.7728899"}, {"lon": "-79.33575", "lat": "43.77296"}, {"lon": "-79.33512", "lat": "43.77313"}, {"lon": "-79.33391", "lat": "43.7733599"}, {"lon": "-79.33268", "lat": "43.77367"}, {"lon": "-79.3325", "lat": "43.77367"}, {"lon": "-79.33249", "lat": "43.77371"}, {"lon": "-79.33242", "lat": "43.77372"}, {"lon": "-79.33237", "lat": "43.77373"}, {"lon": "-79.33229", "lat": "43.77372"}, {"lon": "-79.33224", "lat": "43.77372"}, {"lon": "-79.33205", "lat": "43.77367"}, {"lon": "-79.33178", "lat": "43.7739"}, {"lon": "-79.3316", "lat": "43.77407"}, {"lon": "-79.33149", "lat": "43.7742099"}, {"lon": "-79.33143", "lat": "43.77433"}, {"lon": "-79.33135", "lat": "43.77457"}, {"lon": "-79.33125", "lat": "43.77494"}, {"lon": "-79.33122", "lat": "43.77509"}, {"lon": "-79.33171", "lat": "43.7753"}]}, {"point": [{"lon": "-79.29659", "lat": "43.7106"}, {"lon": "-79.29675", "lat": "43.71069"}, {"lon": "-79.2968099", "lat": "43.71084"}, {"lon": "-79.29707", "lat": "43.71146"}, {"lon": "-79.2973899", "lat": "43.71223"}, {"lon": "-79.29769", "lat": "43.71295"}, {"lon": "-79.29776", "lat": "43.71311"}, {"lon": "-79.29791", "lat": "43.7137"}, {"lon": "-79.29805", "lat": "43.7137699"}, {"lon": "-79.29835", "lat": "43.7145"}, {"lon": "-79.2985099", "lat": "43.71514"}, {"lon": "-79.29863", "lat": "43.71514"}, {"lon": "-79.29865", "lat": "43.7152"}, {"lon": "-79.29895", "lat": "43.7159"}, {"lon": "-79.29915", "lat": "43.71637"}, {"lon": "-79.29927", "lat": "43.71666"}, {"lon": "-79.29951", "lat": "43.71752"}, {"lon": "-79.29978", "lat": "43.71785"}, {"lon": "-79.29997", "lat": "43.7186"}, {"lon": "-79.30017", "lat": "43.71876"}, {"lon": "-79.30055", "lat": "43.7197"}, {"lon": "-79.30058", "lat": "43.71978"}, {"lon": "-79.30088", "lat": "43.72069"}, {"lon": "-79.30101", "lat": "43.7207999"}, {"lon": "-79.30164", "lat": "43.72227"}, {"lon": "-79.30171", "lat": "43.72277"}, {"lon": "-79.30209", "lat": "43.72337"}, {"lon": "-79.30224", "lat": "43.7241"}, {"lon": "-79.3026299", "lat": "43.72472"}, {"lon": "-79.30276", "lat": "43.72537"}]}, {"point": [{"lon": "-79.30276", "lat": "43.72537"}, {"lon": "-79.30292", "lat": "43.72535"}, {"lon": "-79.30328", "lat": "43.72655"}, {"lon": "-79.30346", "lat": "43.72668"}, {"lon": "-79.30394", "lat": "43.72781"}, {"lon": "-79.30397", "lat": "43.7279"}, {"lon": "-79.30412", "lat": "43.72827"}, {"lon": "-79.30437", "lat": "43.72889"}, {"lon": "-79.30449", "lat": "43.72918"}, {"lon": "-79.30447", "lat": "43.72943"}, {"lon": "-79.30499", "lat": "43.7303799"}, {"lon": "-79.3051", "lat": "43.73065"}, {"lon": "-79.3056", "lat": "43.73186"}, {"lon": "-79.30555", "lat": "43.73212"}, {"lon": "-79.30588", "lat": "43.73254"}, {"lon": "-79.3062099", "lat": "43.73336"}, {"lon": "-79.30654", "lat": "43.73456"}, {"lon": "-79.3067499", "lat": "43.73465"}, {"lon": "-79.30741", "lat": "43.73626"}, {"lon": "-79.3074", "lat": "43.73662"}, {"lon": "-79.30764", "lat": "43.73682"}, {"lon": "-79.30772", "lat": "43.73703"}, {"lon": "-79.30832", "lat": "43.73848"}, {"lon": "-79.3082", "lat": "43.73852"}, {"lon": "-79.3084499", "lat": "43.73879"}, {"lon": "-79.30888", "lat": "43.73982"}, {"lon": "-79.30922", "lat": "43.74066"}, {"lon": "-79.30916", "lat": "43.74085"}, {"lon": "-79.30934", "lat": "43.74091"}, {"lon": "-79.30952", "lat": "43.74176"}, {"lon": "-79.30978", "lat": "43.74214"}, {"lon": "-79.31002", "lat": "43.74271"}, {"lon": "-79.31029", "lat": "43.74354"}, {"lon": "-79.31056", "lat": "43.74437"}, {"lon": "-79.31065", "lat": "43.7449"}]}, {"point": [{"lon": "-79.32196", "lat": "43.77342"}, {"lon": "-79.3222", "lat": "43.77349"}, {"lon": "-79.32254", "lat": "43.7742"}, {"lon": "-79.32272", "lat": "43.77508"}, {"lon": "-79.3229999", "lat": "43.7752399"}, {"lon": "-79.32416", "lat": "43.77774"}, {"lon": "-79.32422", "lat": "43.77787"}, {"lon": "-79.32415", "lat": "43.77806"}]}, {"point": [{"lon": "-79.32415", "lat": "43.77806"}, {"lon": "-79.32503", "lat": "43.77958"}, {"lon": "-79.32522", "lat": "43.78024"}, {"lon": "-79.32538", "lat": "43.78034"}, {"lon": "-79.3262699", "lat": "43.78223"}, {"lon": "-79.32626", "lat": "43.78242"}, {"lon": "-79.32639", "lat": "43.78249"}, {"lon": "-79.3269399", "lat": "43.78364"}, {"lon": "-79.32705", "lat": "43.78387"}, {"lon": "-79.3272099", "lat": "43.7842399"}, {"lon": "-79.32719", "lat": "43.78448"}, {"lon": "-79.32792", "lat": "43.78572"}, {"lon": "-79.32798", "lat": "43.78586"}, {"lon": "-79.32791", "lat": "43.78599"}, {"lon": "-79.32899", "lat": "43.78799"}, {"lon": "-79.32941", "lat": "43.78918"}, {"lon": "-79.32957", "lat": "43.78924"}, {"lon": "-79.33077", "lat": "43.7917599"}, {"lon": "-79.33113", "lat": "43.79293"}, {"lon": "-79.3314", "lat": "43.7931"}, {"lon": "-79.3318199", "lat": "43.79401"}, {"lon": "-79.33228", "lat": "43.79505"}, {"lon": "-79.33268", "lat": "43.79596"}, {"lon": "-79.3325799", "lat": "43.79604"}]}, {"point": [{"lon": "-79.34141", "lat": "43.81662"}, {"lon": "-79.3414899", "lat": "43.81668"}, {"lon": "-79.3414899", "lat": "43.81674"}, {"lon": "-79.34154", "lat": "43.81679"}, {"lon": "-79.34161", "lat": "43.81682"}, {"lon": "-79.3417", "lat": "43.8168099"}, {"lon": "-79.34182", "lat": "43.81679"}, {"lon": "-79.34161", "lat": "43.81631"}, {"lon": "-79.3415799", "lat": "43.81591"}, {"lon": "-79.3413099", "lat": "43.81564"}, {"lon": "-79.34124", "lat": "43.8150199"}, {"lon": "-79.34087", "lat": "43.81461"}, {"lon": "-79.34017", "lat": "43.813"}, {"lon": "-79.34026", "lat": "43.81291"}, {"lon": "-79.33978", "lat": "43.81209"}, {"lon": "-79.33938", "lat": "43.81076"}, {"lon": "-79.3392", "lat": "43.81065"}, {"lon": "-79.3388499", "lat": "43.80979"}, {"lon": "-79.3383999", "lat": "43.80874"}, {"lon": "-79.33851", "lat": "43.80865"}, {"lon": "-79.3383", "lat": "43.80852"}, {"lon": "-79.33763", "lat": "43.80704"}, {"lon": "-79.33758", "lat": "43.80652"}, {"lon": "-79.33734", "lat": "43.80639"}, {"lon": "-79.33718", "lat": "43.8060199"}, {"lon": "-79.3366999", "lat": "43.80497"}, {"lon": "-79.33657", "lat": "43.8042299"}, {"lon": "-79.3363", "lat": "43.80408"}, {"lon": "-79.33586", "lat": "43.80306"}, {"lon": "-79.33552", "lat": "43.80232"}, {"lon": "-79.33537", "lat": "43.802"}, {"lon": "-79.33511", "lat": "43.80137"}, {"lon": "-79.33485", "lat": "43.80079"}, {"lon": "-79.33489", "lat": "43.80055"}]}, {"point": [{"lon": "-79.3224199", "lat": "43.77357"}, {"lon": "-79.3222", "lat": "43.77349"}, {"lon": "-79.3220599", "lat": "43.77316"}, {"lon": "-79.32177", "lat": "43.77212"}, {"lon": "-79.32151", "lat": "43.77193"}, {"lon": "-79.32113", "lat": "43.77111"}, {"lon": "-79.3211", "lat": "43.77105"}, {"lon": "-79.32106", "lat": "43.77095"}, {"lon": "-79.32101", "lat": "43.77085"}, {"lon": "-79.32097", "lat": "43.77074"}, {"lon": "-79.32092", "lat": "43.77064"}, {"lon": "-79.32087", "lat": "43.7705399"}, {"lon": "-79.32082", "lat": "43.77044"}, {"lon": "-79.32076", "lat": "43.77033"}, {"lon": "-79.32071", "lat": "43.77023"}, {"lon": "-79.32066", "lat": "43.77013"}, {"lon": "-79.3206", "lat": "43.77003"}, {"lon": "-79.32056", "lat": "43.76995"}, {"lon": "-79.32049", "lat": "43.76983"}, {"lon": "-79.32044", "lat": "43.76973"}, {"lon": "-79.32039", "lat": "43.76965"}, {"lon": "-79.32034", "lat": "43.76956"}, {"lon": "-79.32032", "lat": "43.76952"}, {"lon": "-79.3203", "lat": "43.76948"}, {"lon": "-79.32026", "lat": "43.76939"}, {"lon": "-79.32021", "lat": "43.76931"}, {"lon": "-79.32017", "lat": "43.76923"}, {"lon": "-79.32013", "lat": "43.76914"}, {"lon": "-79.3200899", "lat": "43.76906"}, {"lon": "-79.32005", "lat": "43.76897"}, {"lon": "-79.32001", "lat": "43.76889"}, {"lon": "-79.31998", "lat": "43.7688"}, {"lon": "-79.31994", "lat": "43.76871"}, {"lon": "-79.31992", "lat": "43.7686599"}, {"lon": "-79.3199", "lat": "43.76863"}, {"lon": "-79.31987", "lat": "43.76856"}, {"lon": "-79.31978", "lat": "43.76836"}, {"lon": "-79.3197", "lat": "43.76818"}, {"lon": "-79.31962", "lat": "43.768"}, {"lon": "-79.31958", "lat": "43.7679199"}, {"lon": "-79.31953", "lat": "43.7678"}, {"lon": "-79.31944", "lat": "43.76761"}, {"lon": "-79.31936", "lat": "43.76743"}, {"lon": "-79.3193", "lat": "43.76726"}, {"lon": "-79.31923", "lat": "43.76709"}, {"lon": "-79.31917", "lat": "43.76692"}, {"lon": "-79.3191", "lat": "43.76675"}, {"lon": "-79.31904", "lat": "43.76658"}, {"lon": "-79.31882", "lat": "43.766"}, {"lon": "-79.31858", "lat": "43.76541"}, {"lon": "-79.31843", "lat": "43.76456"}]}, {"point": [{"lon": "-79.3086299", "lat": "43.73887"}, {"lon": "-79.3084499", "lat": "43.73879"}, {"lon": "-79.30832", "lat": "43.73848"}, {"lon": "-79.30772", "lat": "43.73703"}, {"lon": "-79.30764", "lat": "43.73682"}, {"lon": "-79.3076899", "lat": "43.73656"}, {"lon": "-79.30741", "lat": "43.73626"}, {"lon": "-79.30693", "lat": "43.73476"}, {"lon": "-79.3067499", "lat": "43.73465"}, {"lon": "-79.3062099", "lat": "43.73336"}, {"lon": "-79.30588", "lat": "43.73254"}, {"lon": "-79.30583", "lat": "43.73199"}, {"lon": "-79.3056", "lat": "43.73186"}, {"lon": "-79.3051", "lat": "43.73065"}, {"lon": "-79.30499", "lat": "43.7303799"}, {"lon": "-79.30481", "lat": "43.72952"}, {"lon": "-79.30449", "lat": "43.72918"}, {"lon": "-79.30437", "lat": "43.72889"}, {"lon": "-79.30412", "lat": "43.72827"}, {"lon": "-79.30397", "lat": "43.7279"}, {"lon": "-79.30394", "lat": "43.72781"}, {"lon": "-79.30346", "lat": "43.72668"}, {"lon": "-79.30344", "lat": "43.72617"}, {"lon": "-79.30292", "lat": "43.72535"}, {"lon": "-79.30291", "lat": "43.72488"}, {"lon": "-79.3026299", "lat": "43.72472"}, {"lon": "-79.30209", "lat": "43.72337"}, {"lon": "-79.30204", "lat": "43.72283"}]}, {"point": [{"lon": "-79.31065", "lat": "43.7449"}, {"lon": "-79.31078", "lat": "43.74496"}, {"lon": "-79.31093", "lat": "43.7453999"}, {"lon": "-79.31104", "lat": "43.74572"}, {"lon": "-79.31112", "lat": "43.74595"}, {"lon": "-79.31116", "lat": "43.74604"}, {"lon": "-79.3114", "lat": "43.74672"}, {"lon": "-79.3117", "lat": "43.74761"}, {"lon": "-79.3118", "lat": "43.74796"}, {"lon": "-79.31196", "lat": "43.74842"}, {"lon": "-79.31184", "lat": "43.74846"}, {"lon": "-79.3121", "lat": "43.74883"}, {"lon": "-79.31242", "lat": "43.74973"}, {"lon": "-79.31274", "lat": "43.75068"}, {"lon": "-79.31287", "lat": "43.7513999"}, {"lon": "-79.31301", "lat": "43.7514899"}, {"lon": "-79.31325", "lat": "43.75221"}, {"lon": "-79.3133299", "lat": "43.75276"}, {"lon": "-79.31352", "lat": "43.753"}, {"lon": "-79.31379", "lat": "43.75372"}, {"lon": "-79.31386", "lat": "43.75426"}, {"lon": "-79.31401", "lat": "43.75433"}, {"lon": "-79.31433", "lat": "43.75557"}, {"lon": "-79.31448", "lat": "43.7557"}, {"lon": "-79.3146", "lat": "43.75606"}, {"lon": "-79.31482", "lat": "43.75671"}, {"lon": "-79.31523", "lat": "43.75786"}, {"lon": "-79.3152099", "lat": "43.75824"}]}, {"point": [{"lon": "-79.30204", "lat": "43.72283"}, {"lon": "-79.30164", "lat": "43.72227"}, {"lon": "-79.30101", "lat": "43.7207999"}, {"lon": "-79.3007", "lat": "43.71983"}, {"lon": "-79.30058", "lat": "43.71978"}, {"lon": "-79.30055", "lat": "43.7197"}, {"lon": "-79.30017", "lat": "43.71876"}, {"lon": "-79.30028", "lat": "43.71872"}, {"lon": "-79.29978", "lat": "43.71785"}, {"lon": "-79.29927", "lat": "43.71666"}, {"lon": "-79.29931", "lat": "43.71641"}, {"lon": "-79.29915", "lat": "43.71637"}, {"lon": "-79.29895", "lat": "43.7159"}, {"lon": "-79.29865", "lat": "43.7152"}, {"lon": "-79.29863", "lat": "43.71514"}, {"lon": "-79.29866", "lat": "43.71487"}, {"lon": "-79.29835", "lat": "43.7145"}, {"lon": "-79.29822", "lat": "43.71388"}, {"lon": "-79.29805", "lat": "43.7137699"}, {"lon": "-79.29776", "lat": "43.71311"}, {"lon": "-79.29769", "lat": "43.71295"}, {"lon": "-79.2976599", "lat": "43.71256"}, {"lon": "-79.2973899", "lat": "43.71223"}, {"lon": "-79.29707", "lat": "43.71146"}, {"lon": "-79.2968099", "lat": "43.71084"}, {"lon": "-79.29691", "lat": "43.71078"}, {"lon": "-79.29675", "lat": "43.71069"}, {"lon": "-79.29643", "lat": "43.70991"}, {"lon": "-79.29635", "lat": "43.70971"}, {"lon": "-79.29618", "lat": "43.7092699"}, {"lon": "-79.29626", "lat": "43.7089799"}, {"lon": "-79.29597", "lat": "43.70877"}, {"lon": "-79.29571", "lat": "43.70819"}, {"lon": "-79.29527", "lat": "43.70722"}, {"lon": "-79.29497", "lat": "43.7065"}, {"lon": "-79.29498", "lat": "43.70621"}]}, {"point": [{"lon": "-79.29498", "lat": "43.70621"}, {"lon": "-79.29474", "lat": "43.70593"}, {"lon": "-79.2944799", "lat": "43.70535"}, {"lon": "-79.2942", "lat": "43.70471"}, {"lon": "-79.29394", "lat": "43.70387"}, {"lon": "-79.2938099", "lat": "43.70381"}, {"lon": "-79.29365", "lat": "43.70346"}, {"lon": "-79.29346", "lat": "43.70301"}, {"lon": "-79.29312", "lat": "43.7022199"}, {"lon": "-79.29301", "lat": "43.7017"}, {"lon": "-79.29285", "lat": "43.70158"}, {"lon": "-79.29277", "lat": "43.70141"}, {"lon": "-79.29243", "lat": "43.70061"}, {"lon": "-79.29231", "lat": "43.70033"}, {"lon": "-79.29221", "lat": "43.7001"}, {"lon": "-79.29206", "lat": "43.6998"}, {"lon": "-79.2919", "lat": "43.69948"}, {"lon": "-79.2917", "lat": "43.6991"}, {"lon": "-79.29147", "lat": "43.6987"}, {"lon": "-79.29128", "lat": "43.69835"}, {"lon": "-79.29114", "lat": "43.69807"}, {"lon": "-79.29095", "lat": "43.69765"}, {"lon": "-79.29075", "lat": "43.69722"}, {"lon": "-79.29047", "lat": "43.69654"}, {"lon": "-79.29042", "lat": "43.69612"}, {"lon": "-79.29022", "lat": "43.69597"}, {"lon": "-79.28998", "lat": "43.69535"}, {"lon": "-79.28994", "lat": "43.69525"}, {"lon": "-79.2897799", "lat": "43.69487"}, {"lon": "-79.28981", "lat": "43.6948"}, {"lon": "-79.28981", "lat": "43.69441"}, {"lon": "-79.28964", "lat": "43.69428"}, {"lon": "-79.28956", "lat": "43.69423"}, {"lon": "-79.28952", "lat": "43.69412"}, {"lon": "-79.28929", "lat": "43.69358"}, {"lon": "-79.2891999", "lat": "43.69294"}, {"lon": "-79.289", "lat": "43.69287"}, {"lon": "-79.28868", "lat": "43.69208"}, {"lon": "-79.28853", "lat": "43.69169"}, {"lon": "-79.28852", "lat": "43.69166"}, {"lon": "-79.28834", "lat": "43.69123"}, {"lon": "-79.28852", "lat": "43.69136"}]}, {"point": [{"lon": "-79.31843", "lat": "43.76456"}, {"lon": "-79.31815", "lat": "43.76451"}, {"lon": "-79.31811", "lat": "43.7644"}, {"lon": "-79.3180299", "lat": "43.76421"}, {"lon": "-79.3179399", "lat": "43.76396"}, {"lon": "-79.31752", "lat": "43.76301"}, {"lon": "-79.31755", "lat": "43.76273"}, {"lon": "-79.31723", "lat": "43.76237"}, {"lon": "-79.31707", "lat": "43.7620099"}, {"lon": "-79.31703", "lat": "43.76192"}, {"lon": "-79.31688", "lat": "43.7616"}, {"lon": "-79.31661", "lat": "43.76098"}, {"lon": "-79.31631", "lat": "43.76033"}, {"lon": "-79.31616", "lat": "43.75995"}, {"lon": "-79.31622", "lat": "43.75974"}, {"lon": "-79.31607", "lat": "43.7597499"}, {"lon": "-79.31588", "lat": "43.7593699"}, {"lon": "-79.31561", "lat": "43.75876"}, {"lon": "-79.31549", "lat": "43.75806"}, {"lon": "-79.31523", "lat": "43.75786"}, {"lon": "-79.31482", "lat": "43.75671"}, {"lon": "-79.3146", "lat": "43.75606"}, {"lon": "-79.31468", "lat": "43.7558"}]}, {"point": [{"lon": "-79.34524", "lat": "43.7757999"}, {"lon": "-79.34605", "lat": "43.77561"}, {"lon": "-79.34636", "lat": "43.77554"}, {"lon": "-79.34645", "lat": "43.77552"}, {"lon": "-79.34657", "lat": "43.77552"}, {"lon": "-79.3467", "lat": "43.77554"}, {"lon": "-79.34676", "lat": "43.77556"}, {"lon": "-79.3468", "lat": "43.77559"}, {"lon": "-79.34684", "lat": "43.77563"}, {"lon": "-79.34697", "lat": "43.77592"}, {"lon": "-79.34699", "lat": "43.77603"}, {"lon": "-79.34696", "lat": "43.77612"}, {"lon": "-79.34692", "lat": "43.77616"}, {"lon": "-79.34686", "lat": "43.7762"}, {"lon": "-79.3468199", "lat": "43.77621"}, {"lon": "-79.3467299", "lat": "43.77623"}, {"lon": "-79.34667", "lat": "43.77623"}, {"lon": "-79.34659", "lat": "43.77622"}, {"lon": "-79.34613", "lat": "43.77609"}, {"lon": "-79.34591", "lat": "43.77606"}, {"lon": "-79.34563", "lat": "43.77608"}, {"lon": "-79.3449", "lat": "43.77624"}, {"lon": "-79.34406", "lat": "43.77637"}, {"lon": "-79.34397", "lat": "43.77637"}, {"lon": "-79.34392", "lat": "43.77635"}, {"lon": "-79.34389", "lat": "43.77631"}, {"lon": "-79.34372", "lat": "43.77583"}, {"lon": "-79.34305", "lat": "43.7759799"}, {"lon": "-79.34266", "lat": "43.7759"}, {"lon": "-79.3426099", "lat": "43.77607"}, {"lon": "-79.34197", "lat": "43.7761799"}, {"lon": "-79.34165", "lat": "43.77622"}, {"lon": "-79.3413999", "lat": "43.77621"}, {"lon": "-79.33542", "lat": "43.77545"}, {"lon": "-79.33508", "lat": "43.77551"}, {"lon": "-79.3346", "lat": "43.77546"}, {"lon": "-79.33382", "lat": "43.7754"}, {"lon": "-79.33178", "lat": "43.77517"}, {"lon": "-79.33122", "lat": "43.77509"}, {"lon": "-79.33125", "lat": "43.77494"}, {"lon": "-79.33135", "lat": "43.77457"}, {"lon": "-79.33154", "lat": "43.77447"}]}, {"point": [{"lon": "-79.33171", "lat": "43.7753"}, {"lon": "-79.33178", "lat": "43.77517"}, {"lon": "-79.33382", "lat": "43.7754"}, {"lon": "-79.3346", "lat": "43.77546"}, {"lon": "-79.33508", "lat": "43.77551"}, {"lon": "-79.33575", "lat": "43.77575"}, {"lon": "-79.3413999", "lat": "43.77621"}, {"lon": "-79.34165", "lat": "43.77622"}, {"lon": "-79.34197", "lat": "43.7761799"}, {"lon": "-79.3426099", "lat": "43.77607"}, {"lon": "-79.34305", "lat": "43.7759799"}, {"lon": "-79.34372", "lat": "43.77583"}, {"lon": "-79.3445799", "lat": "43.77564"}, {"lon": "-79.34516", "lat": "43.77563"}, {"lon": "-79.3454299", "lat": "43.77546"}, {"lon": "-79.34548", "lat": "43.7755"}, {"lon": "-79.3456099", "lat": "43.77558"}, {"lon": "-79.34568", "lat": "43.77559"}, {"lon": "-79.34575", "lat": "43.7756"}, {"lon": "-79.34585", "lat": "43.77559"}, {"lon": "-79.346", "lat": "43.77556"}, {"lon": "-79.34623", "lat": "43.77552"}, {"lon": "-79.34629", "lat": "43.77552"}, {"lon": "-79.34636", "lat": "43.77554"}, {"lon": "-79.34645", "lat": "43.77552"}, {"lon": "-79.34657", "lat": "43.77552"}, {"lon": "-79.3467", "lat": "43.77554"}, {"lon": "-79.34676", "lat": "43.77556"}, {"lon": "-79.3468", "lat": "43.77559"}, {"lon": "-79.34684", "lat": "43.77563"}, {"lon": "-79.34697", "lat": "43.77592"}, {"lon": "-79.34699", "lat": "43.77603"}, {"lon": "-79.34696", "lat": "43.77612"}, {"lon": "-79.34692", "lat": "43.77616"}, {"lon": "-79.34686", "lat": "43.7762"}, {"lon": "-79.3468199", "lat": "43.77621"}, {"lon": "-79.34675", "lat": "43.77622"}, {"lon": "-79.34671", "lat": "43.77621"}, {"lon": "-79.34662", "lat": "43.7761799"}, {"lon": "-79.3463699", "lat": "43.77602"}, {"lon": "-79.34626", "lat": "43.7759799"}, {"lon": "-79.34615", "lat": "43.77596"}, {"lon": "-79.34605", "lat": "43.77597"}, {"lon": "-79.3453", "lat": "43.77606"}, {"lon": "-79.34518", "lat": "43.77606"}, {"lon": "-79.34509", "lat": "43.77601"}, {"lon": "-79.34505", "lat": "43.77596"}, {"lon": "-79.34504", "lat": "43.77592"}, {"lon": "-79.34506", "lat": "43.77586"}, {"lon": "-79.3451", "lat": "43.77583"}, {"lon": "-79.34524", "lat": "43.7757999"}]}, {"point": [{"lon": "-79.29498", "lat": "43.70621"}, {"lon": "-79.29474", "lat": "43.70593"}, {"lon": "-79.2944799", "lat": "43.70535"}, {"lon": "-79.2942", "lat": "43.70471"}, {"lon": "-79.29394", "lat": "43.70387"}, {"lon": "-79.2938099", "lat": "43.70381"}, {"lon": "-79.29365", "lat": "43.70346"}, {"lon": "-79.29346", "lat": "43.70301"}, {"lon": "-79.29312", "lat": "43.7022199"}, {"lon": "-79.29301", "lat": "43.7017"}, {"lon": "-79.29285", "lat": "43.70158"}, {"lon": "-79.29277", "lat": "43.70141"}, {"lon": "-79.29243", "lat": "43.70061"}, {"lon": "-79.29231", "lat": "43.70033"}, {"lon": "-79.29221", "lat": "43.7001"}, {"lon": "-79.29206", "lat": "43.6998"}, {"lon": "-79.2919", "lat": "43.69948"}, {"lon": "-79.2917", "lat": "43.6991"}, {"lon": "-79.29147", "lat": "43.6987"}, {"lon": "-79.29128", "lat": "43.69835"}, {"lon": "-79.29114", "lat": "43.69807"}, {"lon": "-79.29095", "lat": "43.69765"}, {"lon": "-79.29075", "lat": "43.69722"}, {"lon": "-79.29047", "lat": "43.69654"}, {"lon": "-79.29042", "lat": "43.69612"}, {"lon": "-79.29022", "lat": "43.69597"}, {"lon": "-79.28998", "lat": "43.69535"}, {"lon": "-79.28994", "lat": "43.69525"}, {"lon": "-79.2897799", "lat": "43.69487"}, {"lon": "-79.28981", "lat": "43.6948"}, {"lon": "-79.28964", "lat": "43.69428"}, {"lon": "-79.28956", "lat": "43.69423"}, {"lon": "-79.28952", "lat": "43.69412"}, {"lon": "-79.28929", "lat": "43.69358"}, {"lon": "-79.289", "lat": "43.69287"}, {"lon": "-79.28806", "lat": "43.69308"}, {"lon": "-79.28841", "lat": "43.69391"}, {"lon": "-79.28838", "lat": "43.694"}, {"lon": "-79.28853", "lat": "43.69444"}, {"lon": "-79.28857", "lat": "43.69446"}, {"lon": "-79.28861", "lat": "43.69445"}, {"lon": "-79.28956", "lat": "43.69423"}, {"lon": "-79.28925", "lat": "43.69441"}]}, {"point": [{"lon": "-79.3152099", "lat": "43.75824"}, {"lon": "-79.31561", "lat": "43.75876"}, {"lon": "-79.31588", "lat": "43.7593699"}, {"lon": "-79.31607", "lat": "43.7597499"}, {"lon": "-79.31616", "lat": "43.75995"}, {"lon": "-79.31611", "lat": "43.76019"}, {"lon": "-79.31631", "lat": "43.76033"}, {"lon": "-79.31661", "lat": "43.76098"}, {"lon": "-79.31688", "lat": "43.7616"}, {"lon": "-79.31703", "lat": "43.76192"}, {"lon": "-79.31707", "lat": "43.7620099"}, {"lon": "-79.31723", "lat": "43.76237"}, {"lon": "-79.31716", "lat": "43.76253"}, {"lon": "-79.31752", "lat": "43.76301"}, {"lon": "-79.3179399", "lat": "43.76396"}, {"lon": "-79.3180299", "lat": "43.76421"}, {"lon": "-79.31811", "lat": "43.7644"}, {"lon": "-79.31796", "lat": "43.7644499"}, {"lon": "-79.31815", "lat": "43.76451"}, {"lon": "-79.31858", "lat": "43.76541"}, {"lon": "-79.31882", "lat": "43.766"}, {"lon": "-79.31904", "lat": "43.76658"}, {"lon": "-79.3191", "lat": "43.76675"}, {"lon": "-79.31917", "lat": "43.76692"}, {"lon": "-79.31923", "lat": "43.76709"}, {"lon": "-79.3193", "lat": "43.76726"}, {"lon": "-79.31936", "lat": "43.76743"}, {"lon": "-79.31944", "lat": "43.76761"}, {"lon": "-79.31953", "lat": "43.7678"}, {"lon": "-79.31958", "lat": "43.7679199"}, {"lon": "-79.31961", "lat": "43.76799"}, {"lon": "-79.3197", "lat": "43.76818"}, {"lon": "-79.31978", "lat": "43.76836"}, {"lon": "-79.31987", "lat": "43.76854"}, {"lon": "-79.3199", "lat": "43.76863"}, {"lon": "-79.31992", "lat": "43.7686599"}, {"lon": "-79.31994", "lat": "43.76871"}, {"lon": "-79.31998", "lat": "43.7688"}, {"lon": "-79.32001", "lat": "43.76889"}, {"lon": "-79.32005", "lat": "43.76897"}, {"lon": "-79.3200899", "lat": "43.76906"}, {"lon": "-79.32013", "lat": "43.76914"}, {"lon": "-79.32017", "lat": "43.76923"}, {"lon": "-79.32021", "lat": "43.76931"}, {"lon": "-79.32026", "lat": "43.76939"}, {"lon": "-79.3203", "lat": "43.76948"}, {"lon": "-79.32032", "lat": "43.76952"}, {"lon": "-79.32034", "lat": "43.76956"}, {"lon": "-79.32039", "lat": "43.76965"}, {"lon": "-79.32044", "lat": "43.76973"}, {"lon": "-79.32049", "lat": "43.76983"}, {"lon": "-79.32055", "lat": "43.76993"}, {"lon": "-79.3206", "lat": "43.77003"}, {"lon": "-79.32066", "lat": "43.77013"}, {"lon": "-79.32071", "lat": "43.77023"}, {"lon": "-79.32076", "lat": "43.77033"}, {"lon": "-79.32082", "lat": "43.77044"}, {"lon": "-79.32087", "lat": "43.7705399"}, {"lon": "-79.32092", "lat": "43.77064"}, {"lon": "-79.32097", "lat": "43.77074"}, {"lon": "-79.32101", "lat": "43.77085"}, {"lon": "-79.32106", "lat": "43.77095"}, {"lon": "-79.3211", "lat": "43.77105"}, {"lon": "-79.32113", "lat": "43.77111"}, {"lon": "-79.32125", "lat": "43.7718"}, {"lon": "-79.32151", "lat": "43.77193"}, {"lon": "-79.3220599", "lat": "43.77316"}, {"lon": "-79.32196", "lat": "43.77342"}]}, {"point": [{"lon": "-79.33702", "lat": "43.80599"}, {"lon": "-79.33718", "lat": "43.8060199"}, {"lon": "-79.33734", "lat": "43.80639"}, {"lon": "-79.33763", "lat": "43.80704"}, {"lon": "-79.33813", "lat": "43.80844"}, {"lon": "-79.3383", "lat": "43.80852"}, {"lon": "-79.3383999", "lat": "43.80874"}, {"lon": "-79.3388499", "lat": "43.80979"}, {"lon": "-79.33892", "lat": "43.8103"}, {"lon": "-79.3392", "lat": "43.81065"}, {"lon": "-79.33978", "lat": "43.81209"}, {"lon": "-79.34017", "lat": "43.813"}, {"lon": "-79.34023", "lat": "43.8135199"}, {"lon": "-79.34087", "lat": "43.81461"}, {"lon": "-79.34101", "lat": "43.8153099"}, {"lon": "-79.3413099", "lat": "43.81564"}, {"lon": "-79.34161", "lat": "43.81631"}, {"lon": "-79.34151", "lat": "43.81662"}, {"lon": "-79.34141", "lat": "43.81662"}]}, {"point": [{"lon": "-79.33489", "lat": "43.80055"}, {"lon": "-79.33468", "lat": "43.80042"}, {"lon": "-79.33419", "lat": "43.79931"}, {"lon": "-79.33383", "lat": "43.79818"}, {"lon": "-79.33362", "lat": "43.79804"}, {"lon": "-79.33339", "lat": "43.79756"}, {"lon": "-79.33293", "lat": "43.79652"}, {"lon": "-79.3329", "lat": "43.79609"}, {"lon": "-79.33268", "lat": "43.79596"}, {"lon": "-79.33228", "lat": "43.79505"}, {"lon": "-79.3318199", "lat": "43.79401"}, {"lon": "-79.33166", "lat": "43.7932599"}, {"lon": "-79.3314", "lat": "43.7931"}, {"lon": "-79.33096", "lat": "43.79187"}]}, {"point": [{"lon": "-79.3325799", "lat": "43.79604"}, {"lon": "-79.33293", "lat": "43.79652"}, {"lon": "-79.33339", "lat": "43.79756"}, {"lon": "-79.33342", "lat": "43.79797"}, {"lon": "-79.33362", "lat": "43.79804"}, {"lon": "-79.33419", "lat": "43.79931"}, {"lon": "-79.33468", "lat": "43.80042"}, {"lon": "-79.33456", "lat": "43.80046"}, {"lon": "-79.33485", "lat": "43.80079"}, {"lon": "-79.33511", "lat": "43.80137"}, {"lon": "-79.33537", "lat": "43.802"}, {"lon": "-79.33552", "lat": "43.80232"}, {"lon": "-79.33586", "lat": "43.80306"}, {"lon": "-79.33607", "lat": "43.8039"}, {"lon": "-79.3363", "lat": "43.80408"}, {"lon": "-79.3366999", "lat": "43.80497"}, {"lon": "-79.33702", "lat": "43.80599"}]}, {"point": [{"lon": "-79.31468", "lat": "43.7558"}, {"lon": "-79.31448", "lat": "43.7557"}, {"lon": "-79.31419", "lat": "43.75444"}, {"lon": "-79.31401", "lat": "43.75433"}, {"lon": "-79.31379", "lat": "43.75372"}, {"lon": "-79.31352", "lat": "43.753"}, {"lon": "-79.31367", "lat": "43.75286"}, {"lon": "-79.31325", "lat": "43.75221"}, {"lon": "-79.31317", "lat": "43.7516"}, {"lon": "-79.31301", "lat": "43.7514899"}, {"lon": "-79.31274", "lat": "43.75068"}, {"lon": "-79.31242", "lat": "43.74973"}, {"lon": "-79.3121", "lat": "43.74883"}, {"lon": "-79.31196", "lat": "43.74842"}, {"lon": "-79.3118", "lat": "43.74796"}, {"lon": "-79.3117", "lat": "43.74761"}, {"lon": "-79.3118", "lat": "43.74747"}, {"lon": "-79.3114", "lat": "43.74672"}, {"lon": "-79.31116", "lat": "43.74604"}, {"lon": "-79.31112", "lat": "43.74595"}, {"lon": "-79.31104", "lat": "43.74572"}, {"lon": "-79.31093", "lat": "43.7453999"}, {"lon": "-79.31103", "lat": "43.74524"}, {"lon": "-79.31078", "lat": "43.74496"}, {"lon": "-79.31056", "lat": "43.74437"}, {"lon": "-79.31029", "lat": "43.74354"}, {"lon": "-79.31002", "lat": "43.74271"}, {"lon": "-79.31004", "lat": "43.7423"}, {"lon": "-79.30978", "lat": "43.74214"}, {"lon": "-79.30934", "lat": "43.74091"}, {"lon": "-79.30922", "lat": "43.74066"}, {"lon": "-79.30888", "lat": "43.73982"}, {"lon": "-79.3086299", "lat": "43.73887"}]}, {"point": [{"lon": "-79.3152099", "lat": "43.75824"}, {"lon": "-79.31561", "lat": "43.75876"}, {"lon": "-79.31588", "lat": "43.7593699"}, {"lon": "-79.31607", "lat": "43.7597499"}, {"lon": "-79.31616", "lat": "43.75995"}, {"lon": "-79.31611", "lat": "43.76019"}, {"lon": "-79.31631", "lat": "43.76033"}, {"lon": "-79.31661", "lat": "43.76098"}, {"lon": "-79.31688", "lat": "43.7616"}, {"lon": "-79.31703", "lat": "43.76192"}, {"lon": "-79.31707", "lat": "43.7620099"}, {"lon": "-79.31723", "lat": "43.76237"}, {"lon": "-79.31716", "lat": "43.76253"}, {"lon": "-79.31752", "lat": "43.76301"}, {"lon": "-79.3179399", "lat": "43.76396"}, {"lon": "-79.3180299", "lat": "43.76421"}, {"lon": "-79.31811", "lat": "43.7644"}, {"lon": "-79.31796", "lat": "43.7644499"}, {"lon": "-79.31815", "lat": "43.76451"}, {"lon": "-79.31858", "lat": "43.76541"}, {"lon": "-79.31882", "lat": "43.766"}, {"lon": "-79.31904", "lat": "43.76658"}, {"lon": "-79.3191", "lat": "43.76675"}, {"lon": "-79.31917", "lat": "43.76692"}, {"lon": "-79.31923", "lat": "43.76709"}, {"lon": "-79.3193", "lat": "43.76726"}, {"lon": "-79.31936", "lat": "43.76743"}, {"lon": "-79.31944", "lat": "43.76761"}, {"lon": "-79.31953", "lat": "43.7678"}, {"lon": "-79.31958", "lat": "43.7679199"}, {"lon": "-79.31961", "lat": "43.76799"}, {"lon": "-79.3197", "lat": "43.76818"}, {"lon": "-79.31978", "lat": "43.76836"}, {"lon": "-79.31987", "lat": "43.76854"}, {"lon": "-79.3199", "lat": "43.76863"}, {"lon": "-79.31992", "lat": "43.7686599"}, {"lon": "-79.31994", "lat": "43.76871"}, {"lon": "-79.31998", "lat": "43.7688"}, {"lon": "-79.32001", "lat": "43.76889"}, {"lon": "-79.32005", "lat": "43.76897"}, {"lon": "-79.3200899", "lat": "43.76906"}, {"lon": "-79.32013", "lat": "43.76914"}, {"lon": "-79.32017", "lat": "43.76923"}, {"lon": "-79.32021", "lat": "43.76931"}, {"lon": "-79.32026", "lat": "43.76939"}, {"lon": "-79.3203", "lat": "43.76948"}, {"lon": "-79.32032", "lat": "43.76952"}, {"lon": "-79.32034", "lat": "43.76956"}, {"lon": "-79.32039", "lat": "43.76965"}, {"lon": "-79.32044", "lat": "43.76973"}, {"lon": "-79.32049", "lat": "43.76983"}, {"lon": "-79.32055", "lat": "43.76993"}, {"lon": "-79.3206", "lat": "43.77003"}, {"lon": "-79.32066", "lat": "43.77013"}, {"lon": "-79.32071", "lat": "43.77023"}, {"lon": "-79.32076", "lat": "43.77033"}, {"lon": "-79.32082", "lat": "43.77044"}, {"lon": "-79.32087", "lat": "43.7705399"}, {"lon": "-79.32092", "lat": "43.77064"}, {"lon": "-79.32097", "lat": "43.77074"}, {"lon": "-79.32101", "lat": "43.77085"}, {"lon": "-79.32106", "lat": "43.77095"}, {"lon": "-79.3211", "lat": "43.77105"}, {"lon": "-79.32113", "lat": "43.77111"}, {"lon": "-79.32151", "lat": "43.77193"}, {"lon": "-79.3223", "lat": "43.77188"}]}, {"point": [{"lon": "-79.33154", "lat": "43.77447"}, {"lon": "-79.33143", "lat": "43.77433"}, {"lon": "-79.33149", "lat": "43.7742099"}, {"lon": "-79.3316", "lat": "43.77407"}, {"lon": "-79.33178", "lat": "43.7739"}, {"lon": "-79.33205", "lat": "43.77367"}, {"lon": "-79.33224", "lat": "43.77372"}, {"lon": "-79.33229", "lat": "43.77372"}, {"lon": "-79.33234", "lat": "43.77373"}, {"lon": "-79.33242", "lat": "43.77372"}, {"lon": "-79.33249", "lat": "43.77371"}, {"lon": "-79.33256", "lat": "43.77376"}, {"lon": "-79.33268", "lat": "43.77367"}, {"lon": "-79.33446", "lat": "43.7733599"}, {"lon": "-79.33512", "lat": "43.77313"}, {"lon": "-79.33599", "lat": "43.77301"}, {"lon": "-79.33622", "lat": "43.7728899"}, {"lon": "-79.33583", "lat": "43.77194"}, {"lon": "-79.33569", "lat": "43.77163"}, {"lon": "-79.33559", "lat": "43.77152"}, {"lon": "-79.33544", "lat": "43.77126"}, {"lon": "-79.3349099", "lat": "43.77078"}, {"lon": "-79.33477", "lat": "43.77061"}, {"lon": "-79.33469", "lat": "43.77056"}, {"lon": "-79.33459", "lat": "43.7705399"}, {"lon": "-79.3345", "lat": "43.77055"}, {"lon": "-79.33408", "lat": "43.77064"}, {"lon": "-79.33199", "lat": "43.77104"}, {"lon": "-79.33185", "lat": "43.77112"}, {"lon": "-79.33146", "lat": "43.77119"}, {"lon": "-79.33142", "lat": "43.77105"}, {"lon": "-79.33136", "lat": "43.77091"}, {"lon": "-79.33129", "lat": "43.77078"}, {"lon": "-79.33122", "lat": "43.77068"}, {"lon": "-79.33113", "lat": "43.7706"}, {"lon": "-79.3310599", "lat": "43.7705399"}, {"lon": "-79.33098", "lat": "43.77051"}, {"lon": "-79.33089", "lat": "43.77047"}, {"lon": "-79.33076", "lat": "43.77043"}, {"lon": "-79.33058", "lat": "43.7704"}, {"lon": "-79.33043", "lat": "43.77041"}, {"lon": "-79.33028", "lat": "43.77043"}, {"lon": "-79.33022", "lat": "43.77037"}, {"lon": "-79.33013", "lat": "43.77046"}, {"lon": "-79.3299", "lat": "43.7705"}, {"lon": "-79.32963", "lat": "43.77053"}, {"lon": "-79.32809", "lat": "43.77063"}, {"lon": "-79.32751", "lat": "43.77061"}, {"lon": "-79.3260899", "lat": "43.77077"}, {"lon": "-79.32518", "lat": "43.77084"}, {"lon": "-79.32513", "lat": "43.77084"}, {"lon": "-79.32505", "lat": "43.77084"}, {"lon": "-79.32494", "lat": "43.77086"}, {"lon": "-79.32482", "lat": "43.77091"}, {"lon": "-79.32471", "lat": "43.77097"}, {"lon": "-79.32462", "lat": "43.77105"}, {"lon": "-79.32425", "lat": "43.77135"}, {"lon": "-79.3242099", "lat": "43.77138"}, {"lon": "-79.32408", "lat": "43.77144"}, {"lon": "-79.32397", "lat": "43.77149"}, {"lon": "-79.32382", "lat": "43.77153"}, {"lon": "-79.32373", "lat": "43.77154"}, {"lon": "-79.32343", "lat": "43.77152"}, {"lon": "-79.32328", "lat": "43.77161"}, {"lon": "-79.32231", "lat": "43.77176"}, {"lon": "-79.32151", "lat": "43.77193"}, {"lon": "-79.32113", "lat": "43.77111"}, {"lon": "-79.3211", "lat": "43.77105"}, {"lon": "-79.32106", "lat": "43.77095"}, {"lon": "-79.32101", "lat": "43.77085"}, {"lon": "-79.32097", "lat": "43.77074"}, {"lon": "-79.32092", "lat": "43.77064"}, {"lon": "-79.32087", "lat": "43.7705399"}, {"lon": "-79.32082", "lat": "43.77044"}, {"lon": "-79.32076", "lat": "43.77033"}, {"lon": "-79.32071", "lat": "43.77023"}, {"lon": "-79.32066", "lat": "43.77013"}, {"lon": "-79.3206", "lat": "43.77003"}, {"lon": "-79.32056", "lat": "43.76995"}, {"lon": "-79.32049", "lat": "43.76983"}, {"lon": "-79.32044", "lat": "43.76973"}, {"lon": "-79.32039", "lat": "43.76965"}, {"lon": "-79.32034", "lat": "43.76956"}, {"lon": "-79.32032", "lat": "43.76952"}, {"lon": "-79.3203", "lat": "43.76948"}, {"lon": "-79.32026", "lat": "43.76939"}, {"lon": "-79.32021", "lat": "43.76931"}, {"lon": "-79.32017", "lat": "43.76923"}, {"lon": "-79.32013", "lat": "43.76914"}, {"lon": "-79.3200899", "lat": "43.76906"}, {"lon": "-79.32005", "lat": "43.76897"}, {"lon": "-79.32001", "lat": "43.76889"}, {"lon": "-79.31998", "lat": "43.7688"}, {"lon": "-79.31994", "lat": "43.76871"}, {"lon": "-79.31992", "lat": "43.7686599"}, {"lon": "-79.3199", "lat": "43.76863"}, {"lon": "-79.31987", "lat": "43.76856"}, {"lon": "-79.31978", "lat": "43.76836"}, {"lon": "-79.3197", "lat": "43.76818"}, {"lon": "-79.31962", "lat": "43.768"}, {"lon": "-79.31958", "lat": "43.7679199"}, {"lon": "-79.31953", "lat": "43.7678"}, {"lon": "-79.31944", "lat": "43.76761"}, {"lon": "-79.31936", "lat": "43.76743"}, {"lon": "-79.3193", "lat": "43.76726"}, {"lon": "-79.31923", "lat": "43.76709"}, {"lon": "-79.31917", "lat": "43.76692"}, {"lon": "-79.3191", "lat": "43.76675"}, {"lon": "-79.31904", "lat": "43.76658"}, {"lon": "-79.31882", "lat": "43.766"}, {"lon": "-79.31858", "lat": "43.76541"}, {"lon": "-79.31843", "lat": "43.76456"}]}, {"point": [{"lon": "-79.29498", "lat": "43.70621"}, {"lon": "-79.29474", "lat": "43.70593"}, {"lon": "-79.2944799", "lat": "43.70535"}, {"lon": "-79.2942", "lat": "43.70471"}, {"lon": "-79.29394", "lat": "43.70387"}, {"lon": "-79.2938099", "lat": "43.70381"}, {"lon": "-79.29365", "lat": "43.70346"}, {"lon": "-79.29346", "lat": "43.70301"}, {"lon": "-79.29312", "lat": "43.7022199"}, {"lon": "-79.29301", "lat": "43.7017"}, {"lon": "-79.29285", "lat": "43.70158"}, {"lon": "-79.29277", "lat": "43.70141"}, {"lon": "-79.29243", "lat": "43.70061"}, {"lon": "-79.29231", "lat": "43.70033"}, {"lon": "-79.29221", "lat": "43.7001"}, {"lon": "-79.29206", "lat": "43.6998"}, {"lon": "-79.2919", "lat": "43.69948"}, {"lon": "-79.2917", "lat": "43.6991"}, {"lon": "-79.29147", "lat": "43.6987"}, {"lon": "-79.29128", "lat": "43.69835"}, {"lon": "-79.29114", "lat": "43.69807"}, {"lon": "-79.29095", "lat": "43.69765"}, {"lon": "-79.29075", "lat": "43.69722"}, {"lon": "-79.29047", "lat": "43.69654"}, {"lon": "-79.29042", "lat": "43.69612"}, {"lon": "-79.29022", "lat": "43.69597"}, {"lon": "-79.28998", "lat": "43.69535"}, {"lon": "-79.28994", "lat": "43.69525"}, {"lon": "-79.2897799", "lat": "43.69487"}, {"lon": "-79.28981", "lat": "43.6948"}, {"lon": "-79.28964", "lat": "43.69428"}, {"lon": "-79.28956", "lat": "43.69423"}, {"lon": "-79.28952", "lat": "43.69412"}, {"lon": "-79.28929", "lat": "43.69358"}, {"lon": "-79.289", "lat": "43.69287"}, {"lon": "-79.28806", "lat": "43.69308"}, {"lon": "-79.28841", "lat": "43.69391"}, {"lon": "-79.28838", "lat": "43.694"}, {"lon": "-79.28853", "lat": "43.69444"}, {"lon": "-79.28857", "lat": "43.69446"}, {"lon": "-79.28861", "lat": "43.69445"}, {"lon": "-79.28956", "lat": "43.69423"}, {"lon": "-79.2887", "lat": "43.69448"}]}, {"point": [{"lon": "-79.33096", "lat": "43.79187"}, {"lon": "-79.33077", "lat": "43.7917599"}, {"lon": "-79.32979", "lat": "43.78933"}, {"lon": "-79.32957", "lat": "43.78924"}, {"lon": "-79.32899", "lat": "43.78799"}, {"lon": "-79.32798", "lat": "43.78586"}, {"lon": "-79.32813", "lat": "43.78582"}, {"lon": "-79.32792", "lat": "43.78572"}, {"lon": "-79.3272099", "lat": "43.7842399"}, {"lon": "-79.32725", "lat": "43.78395"}, {"lon": "-79.32705", "lat": "43.78387"}, {"lon": "-79.3269399", "lat": "43.78364"}, {"lon": "-79.32639", "lat": "43.78249"}, {"lon": "-79.3262699", "lat": "43.78223"}, {"lon": "-79.32641", "lat": "43.78219"}, {"lon": "-79.3256", "lat": "43.78047"}, {"lon": "-79.32538", "lat": "43.78034"}, {"lon": "-79.32503", "lat": "43.77958"}, {"lon": "-79.32422", "lat": "43.77787"}, {"lon": "-79.32437", "lat": "43.77783"}, {"lon": "-79.32416", "lat": "43.77774"}, {"lon": "-79.32332", "lat": "43.77551"}, {"lon": "-79.3229999", "lat": "43.7752399"}, {"lon": "-79.32254", "lat": "43.7742"}, {"lon": "-79.3224199", "lat": "43.77357"}]}, {"point": [{"lon": "-79.28818", "lat": "43.69108"}, {"lon": "-79.28834", "lat": "43.69123"}, {"lon": "-79.28852", "lat": "43.69166"}, {"lon": "-79.28853", "lat": "43.69169"}, {"lon": "-79.28868", "lat": "43.69208"}, {"lon": "-79.28877", "lat": "43.69263"}, {"lon": "-79.289", "lat": "43.69287"}, {"lon": "-79.28929", "lat": "43.69358"}, {"lon": "-79.28952", "lat": "43.69412"}, {"lon": "-79.28937", "lat": "43.69421"}, {"lon": "-79.28956", "lat": "43.69423"}, {"lon": "-79.28952", "lat": "43.6943"}, {"lon": "-79.28972", "lat": "43.69482"}, {"lon": "-79.2897799", "lat": "43.69487"}, {"lon": "-79.28994", "lat": "43.69525"}, {"lon": "-79.28998", "lat": "43.69535"}, {"lon": "-79.29022", "lat": "43.69597"}, {"lon": "-79.2903", "lat": "43.69642"}, {"lon": "-79.29047", "lat": "43.69654"}, {"lon": "-79.29075", "lat": "43.69722"}, {"lon": "-79.29095", "lat": "43.69765"}, {"lon": "-79.29114", "lat": "43.69807"}, {"lon": "-79.29128", "lat": "43.69835"}, {"lon": "-79.29147", "lat": "43.6987"}, {"lon": "-79.2917", "lat": "43.6991"}, {"lon": "-79.2919", "lat": "43.69948"}, {"lon": "-79.29206", "lat": "43.6998"}, {"lon": "-79.29221", "lat": "43.7001"}, {"lon": "-79.29231", "lat": "43.70033"}, {"lon": "-79.29243", "lat": "43.70061"}, {"lon": "-79.29277", "lat": "43.70141"}, {"lon": "-79.29276", "lat": "43.70151"}, {"lon": "-79.29285", "lat": "43.70158"}, {"lon": "-79.29312", "lat": "43.7022199"}, {"lon": "-79.29346", "lat": "43.70301"}, {"lon": "-79.29355", "lat": "43.70338"}, {"lon": "-79.29365", "lat": "43.70346"}, {"lon": "-79.2938099", "lat": "43.70381"}, {"lon": "-79.2942", "lat": "43.70471"}, {"lon": "-79.29442", "lat": "43.70536"}, {"lon": "-79.2944799", "lat": "43.70535"}, {"lon": "-79.29474", "lat": "43.70593"}, {"lon": "-79.29497", "lat": "43.7065"}, {"lon": "-79.2949", "lat": "43.70661"}, {"lon": "-79.29527", "lat": "43.70722"}, {"lon": "-79.29571", "lat": "43.70819"}, {"lon": "-79.29577", "lat": "43.70862"}, {"lon": "-79.29597", "lat": "43.70877"}, {"lon": "-79.29618", "lat": "43.7092699"}, {"lon": "-79.29635", "lat": "43.70971"}, {"lon": "-79.29643", "lat": "43.70991"}, {"lon": "-79.29659", "lat": "43.7106"}]}, {"point": [{"lon": "-79.2887", "lat": "43.69448"}, {"lon": "-79.28956", "lat": "43.69423"}, {"lon": "-79.28952", "lat": "43.6943"}, {"lon": "-79.28972", "lat": "43.69482"}, {"lon": "-79.2897799", "lat": "43.69487"}, {"lon": "-79.28994", "lat": "43.69525"}, {"lon": "-79.28998", "lat": "43.69535"}, {"lon": "-79.29022", "lat": "43.69597"}, {"lon": "-79.2903", "lat": "43.69642"}, {"lon": "-79.29047", "lat": "43.69654"}, {"lon": "-79.29075", "lat": "43.69722"}, {"lon": "-79.29095", "lat": "43.69765"}, {"lon": "-79.29114", "lat": "43.69807"}, {"lon": "-79.29128", "lat": "43.69835"}, {"lon": "-79.29147", "lat": "43.6987"}, {"lon": "-79.2917", "lat": "43.6991"}, {"lon": "-79.2919", "lat": "43.69948"}, {"lon": "-79.29206", "lat": "43.6998"}, {"lon": "-79.29221", "lat": "43.7001"}, {"lon": "-79.29231", "lat": "43.70033"}, {"lon": "-79.29243", "lat": "43.70061"}, {"lon": "-79.29277", "lat": "43.70141"}, {"lon": "-79.29276", "lat": "43.70151"}, {"lon": "-79.29285", "lat": "43.70158"}, {"lon": "-79.29312", "lat": "43.7022199"}, {"lon": "-79.29346", "lat": "43.70301"}, {"lon": "-79.29355", "lat": "43.70338"}, {"lon": "-79.29365", "lat": "43.70346"}, {"lon": "-79.2938099", "lat": "43.70381"}, {"lon": "-79.2942", "lat": "43.70471"}, {"lon": "-79.29442", "lat": "43.70536"}, {"lon": "-79.2944799", "lat": "43.70535"}, {"lon": "-79.29474", "lat": "43.70593"}, {"lon": "-79.29497", "lat": "43.7065"}, {"lon": "-79.2949", "lat": "43.70661"}, {"lon": "-79.29527", "lat": "43.70722"}, {"lon": "-79.29571", "lat": "43.70819"}, {"lon": "-79.29577", "lat": "43.70862"}, {"lon": "-79.29597", "lat": "43.70877"}, {"lon": "-79.29618", "lat": "43.7092699"}, {"lon": "-79.29635", "lat": "43.70971"}, {"lon": "-79.29643", "lat": "43.70991"}, {"lon": "-79.29659", "lat": "43.7106"}]}, {"point": [{"lon": "-79.28925", "lat": "43.69441"}, {"lon": "-79.28956", "lat": "43.69423"}, {"lon": "-79.28952", "lat": "43.6943"}, {"lon": "-79.28972", "lat": "43.69482"}, {"lon": "-79.2897799", "lat": "43.69487"}, {"lon": "-79.28994", "lat": "43.69525"}, {"lon": "-79.28998", "lat": "43.69535"}, {"lon": "-79.29022", "lat": "43.69597"}, {"lon": "-79.2903", "lat": "43.69642"}, {"lon": "-79.29047", "lat": "43.69654"}, {"lon": "-79.29075", "lat": "43.69722"}, {"lon": "-79.29095", "lat": "43.69765"}, {"lon": "-79.29114", "lat": "43.69807"}, {"lon": "-79.29128", "lat": "43.69835"}, {"lon": "-79.29147", "lat": "43.6987"}, {"lon": "-79.2917", "lat": "43.6991"}, {"lon": "-79.2919", "lat": "43.69948"}, {"lon": "-79.29206", "lat": "43.6998"}, {"lon": "-79.29221", "lat": "43.7001"}, {"lon": "-79.29231", "lat": "43.70033"}, {"lon": "-79.29243", "lat": "43.70061"}, {"lon": "-79.29277", "lat": "43.70141"}, {"lon": "-79.29276", "lat": "43.70151"}, {"lon": "-79.29285", "lat": "43.70158"}, {"lon": "-79.29312", "lat": "43.7022199"}, {"lon": "-79.29346", "lat": "43.70301"}, {"lon": "-79.29355", "lat": "43.70338"}, {"lon": "-79.29365", "lat": "43.70346"}, {"lon": "-79.2938099", "lat": "43.70381"}, {"lon": "-79.2942", "lat": "43.70471"}, {"lon": "-79.29442", "lat": "43.70536"}, {"lon": "-79.2944799", "lat": "43.70535"}, {"lon": "-79.29474", "lat": "43.70593"}, {"lon": "-79.29497", "lat": "43.7065"}, {"lon": "-79.2949", "lat": "43.70661"}, {"lon": "-79.29527", "lat": "43.70722"}, {"lon": "-79.29571", "lat": "43.70819"}, {"lon": "-79.29577", "lat": "43.70862"}, {"lon": "-79.29597", "lat": "43.70877"}, {"lon": "-79.29618", "lat": "43.7092699"}, {"lon": "-79.29635", "lat": "43.70971"}, {"lon": "-79.29643", "lat": "43.70991"}, {"lon": "-79.29659", "lat": "43.7106"}]}], "lonMax": "-79.28818", "color": "ff0000", "oppositeColor": "ffffff", "stop": [{"stopId": "14628", "lon": "-79.34524", "tag": "14150", "title": "Don Mills Station", "lat": "43.7757999"}, {"stopId": "13705", "lon": "-79.34266", "tag": "5480", "title": "Sheppard Ave East At Parkway Forest Dr East Side", "lat": "43.7759"}, {"stopId": "7190", "lon": "-79.33542", "tag": "4699", "title": "2025 Sheppard Ave East", "lat": "43.77545"}, {"stopId": "13683", "lon": "-79.33154", "tag": "6700", "title": "Consumers Rd At Sheppard Ave East South Side", "lat": "43.7744699"}, {"stopId": "7476", "lon": "-79.3325599", "tag": "10234", "title": "Yorkland Blvd (North) At Consumers Rd West Side", "lat": "43.7737599"}, {"stopId": "7475", "lon": "-79.33446", "tag": "2941", "title": "279 Yorkland Blvd (North)", "lat": "43.7733599"}, {"stopId": "7477", "lon": "-79.33599", "tag": "3439", "title": "Yorkland Blvd (North) At Yorkland Rd", "lat": "43.7730099"}, {"stopId": "13684", "lon": "-79.3354399", "tag": "7789", "title": "185 Yorkland Blvd", "lat": "43.7712599"}, {"stopId": "13685", "lon": "-79.3319899", "tag": "3984", "title": "Yorkland Blvd (South) At Consumers Rd", "lat": "43.77104"}, {"stopId": "13686", "lon": "-79.3302199", "tag": "6666", "title": "251 Consumers Rd", "lat": "43.77037"}, {"stopId": "12352", "lon": "-79.32751", "tag": "8828", "title": "501 Consumers Rd", "lat": "43.77061"}, {"stopId": "13687", "lon": "-79.32343", "tag": "5137", "title": "Consumers Rd At Hallcrown Pl", "lat": "43.77152"}, {"stopId": "7414", "lon": "-79.31843", "tag": "2288", "title": "Victoria Park Ave At Farm Greenway", "lat": "43.7645599"}, {"stopId": "8523", "lon": "-79.3175499", "tag": "9946", "title": "Victoria Park Ave At York Mills Rd South Side", "lat": "43.7627299"}, {"stopId": "7418", "lon": "-79.3162199", "tag": "4218", "title": "Victoria Park Ave At Paget Rd South Side", "lat": "43.75974"}, {"stopId": "8490", "lon": "-79.31549", "tag": "10088", "title": "Victoria Park Ave At Parkwoods Village Dr", "lat": "43.75806"}, {"stopId": "8439", "lon": "-79.31468", "tag": "7892", "title": "Victoria Park Ave At Combermere Dr South Side", "lat": "43.7557999"}, {"stopId": "10730", "lon": "-79.31419", "tag": "8530", "title": "Victoria Park Ave At Cassandra Blvd", "lat": "43.75444"}, {"stopId": "8472", "lon": "-79.3136699", "tag": "8006", "title": "Victoria Park Ave At Ivordale Cres (South) South Side", "lat": "43.7528599"}, {"stopId": "14272", "lon": "-79.31317", "tag": "1986", "title": "Victoria Park Ave At Rowena Dr", "lat": "43.7516"}, {"stopId": "8445", "lon": "-79.3117999", "tag": "8310", "title": "Victoria Park Ave At Curlew Dr South Side", "lat": "43.7474699"}, {"stopId": "8448", "lon": "-79.3110299", "tag": "1453", "title": "Victoria Park Ave At Deanvar Ave South Side", "lat": "43.7452399"}, {"stopId": "8478", "lon": "-79.3100399", "tag": "1401", "title": "Victoria Park Ave At Lawrence Ave East", "lat": "43.7422999"}, {"stopId": "8500", "lon": "-79.30863", "tag": "749", "title": "Victoria Park Ave At Sloane Ave", "lat": "43.7388699"}, {"stopId": "8513", "lon": "-79.3076899", "tag": "6829", "title": "Victoria Park Ave At Sweeney Dr South Side", "lat": "43.73656"}, {"stopId": "8496", "lon": "-79.3069299", "tag": "2717", "title": "Victoria Park Ave At Ruscica Dr", "lat": "43.7347599"}, {"stopId": "8450", "lon": "-79.3058299", "tag": "1803", "title": "Victoria Park Ave At Draycott Dr South Side", "lat": "43.7319899"}, {"stopId": "8457", "lon": "-79.3048099", "tag": "1781", "title": "Victoria Park Ave At Elvaston Dr South Side", "lat": "43.7295199"}, {"stopId": "8441", "lon": "-79.30344", "tag": "3970", "title": "Victoria Park Ave At Jonesville Cres South Side", "lat": "43.72617"}, {"stopId": "8453", "lon": "-79.30291", "tag": "9280", "title": "Victoria Park Ave At Eglinton Ave East", "lat": "43.72488"}, {"stopId": "8427", "lon": "-79.30204", "tag": "2096", "title": "Victoria Park Ave At O'Connor Dr South Side", "lat": "43.7228299"}, {"stopId": "16695", "lon": "-79.3006999", "tag": "25094", "title": "Victoria Park Ave At Sunrise Ave", "lat": "43.7198299"}, {"stopId": "8520", "lon": "-79.3002799", "tag": "6820", "title": "Victoria Park Ave At Valdane Dr", "lat": "43.7187199"}, {"stopId": "8491", "lon": "-79.2993099", "tag": "2517", "title": "Victoria Park Ave At Parma Crt South Side", "lat": "43.7164099"}, {"stopId": "8429", "lon": "-79.2986599", "tag": "8750", "title": "Victoria Park Ave At Amsterdam Ave South Side", "lat": "43.7148699"}, {"stopId": "8522", "lon": "-79.29822", "tag": "4046", "title": "Victoria Park Ave At Yardley Ave", "lat": "43.71388"}, {"stopId": "8463", "lon": "-79.2976599", "tag": "7449", "title": "Victoria Park Ave At Furnival Rd", "lat": "43.7125599"}, {"stopId": "8493", "lon": "-79.2969099", "tag": "9831", "title": "Victoria Park Ave At Peard Rd", "lat": "43.71078"}, {"stopId": "8504", "lon": "-79.2962599", "tag": "6315", "title": "Victoria Park Ave At St Clair Ave East", "lat": "43.70898"}, {"stopId": "8447", "lon": "-79.29498", "tag": "9165", "title": "Victoria Park Ave At Dawes Rd South Side", "lat": "43.7062099"}, {"stopId": "8495", "lon": "-79.2939399", "tag": "5235", "title": "Victoria Park Ave At Ripon Rd", "lat": "43.7038699"}, {"stopId": "16463", "lon": "-79.2930099", "tag": "24789", "title": "Victoria Park Ave At Conroy Ave", "lat": "43.7016999"}, {"stopId": "15026", "lon": "-79.29042", "tag": "14797", "title": "Victoria Park Ave At Crescent Town Rd South Side", "lat": "43.69612"}, {"lon": "-79.2887", "tag": "14733_ar", "title": "Victoria Park Station", "lat": "43.6944799"}, {"stopId": "7946", "lon": "-79.34141", "tag": "1680", "title": "Victoria Park Ave Loop At Steeles Ave East", "lat": "43.8166199"}, {"stopId": "8509", "lon": "-79.3415799", "tag": "3956", "title": "Victoria Park Ave At Steeles Ave East", "lat": "43.8159099"}, {"stopId": "8510", "lon": "-79.3412399", "tag": "6055", "title": "Victoria Park Ave At Steeles Ave East South Side", "lat": "43.8150199"}, {"stopId": "9523", "lon": "-79.3402599", "tag": "3149", "title": "3900 Victoria Park Ave", "lat": "43.81291"}, {"stopId": "8465", "lon": "-79.33938", "tag": "7009", "title": "Victoria Park Ave At Gordon Baker Rd", "lat": "43.81076"}, {"stopId": "8503", "lon": "-79.3385099", "tag": "7592", "title": "Victoria Park Ave At Sparks Ave", "lat": "43.80865"}, {"stopId": "8516", "lon": "-79.33758", "tag": "2326", "title": "Victoria Park Ave At Tempo Ave", "lat": "43.80652"}, {"stopId": "8479", "lon": "-79.33657", "tag": "2609", "title": "Victoria Park Ave At McNicoll Ave", "lat": "43.80423"}, {"stopId": "8487", "lon": "-79.33489", "tag": "3931", "title": "Victoria Park Ave At Navaho Dr", "lat": "43.8005499"}, {"stopId": "8492", "lon": "-79.33383", "tag": "9293", "title": "Victoria Park Ave At Pawnee Ave", "lat": "43.79818"}, {"stopId": "8468", "lon": "-79.3329", "tag": "1194", "title": "Victoria Park Ave At Hare Gate", "lat": "43.79609"}, {"stopId": "8461", "lon": "-79.3316599", "tag": "4878", "title": "Victoria Park Ave At Finch Ave East", "lat": "43.7932599"}, {"stopId": "8458", "lon": "-79.33096", "tag": "5515", "title": "Victoria Park Ave At Ernest Ave", "lat": "43.7918699"}, {"stopId": "8521", "lon": "-79.32979", "tag": "9737", "title": "Victoria Park Ave At Van Horne Ave", "lat": "43.78933"}, {"stopId": "7421", "lon": "-79.3281299", "tag": "2670", "title": "Victoria Park Ave At Pleasant View Dr", "lat": "43.7858199"}, {"stopId": "8438", "lon": "-79.3272499", "tag": "3660", "title": "Victoria Park Ave At Clydesdale Dr", "lat": "43.7839499"}, {"stopId": "8489", "lon": "-79.3264099", "tag": "1487", "title": "Opposite 2791 Victoria Park Ave", "lat": "43.78219"}, {"stopId": "8488", "lon": "-79.3255999", "tag": "6220", "title": "Victoria Park Ave At Old Sheppard Ave", "lat": "43.7804699"}, {"stopId": "7420", "lon": "-79.3243699", "tag": "4225", "title": "Victoria Park Ave At Patrick Blvd", "lat": "43.7778299"}, {"stopId": "7426", "lon": "-79.3233199", "tag": "7615", "title": "Victoria Park Ave At Sheppard Ave East", "lat": "43.7755099"}, {"stopId": "7413", "lon": "-79.32242", "tag": "9920", "title": "Victoria Park Ave At Lansing Sq", "lat": "43.7735699"}, {"stopId": "7411", "lon": "-79.3217699", "tag": "3012", "title": "Victoria Park Ave At Consumers Rd", "lat": "43.7721199"}, {"stopId": "14963", "lon": "-79.2898099", "tag": "14700", "title": "Victoria Park Ave At Victoria Park Station", "lat": "43.6944099"}, {"stopId": "14962", "lon": "-79.2891999", "tag": "14731", "title": "Victoria Park Ave At Denton Ave", "lat": "43.6929399"}, {"stopId": "4690", "lon": "-79.28852", "tag": "8504", "title": "Victoria Park Ave At Danforth Ave", "lat": "43.6913599"}, {"lon": "-79.28925", "tag": "14734_ar", "title": "Victoria Park Station", "lat": "43.6944099"}, {"stopId": "14975", "lon": "-79.2887", "tag": "14733", "title": "Victoria Park Station", "lat": "43.6944799"}, {"stopId": "8443", "lon": "-79.2902999", "tag": "4384", "title": "Victoria Park Ave At Crescent Town Rd", "lat": "43.6964199"}, {"stopId": "8440", "lon": "-79.29276", "tag": "6679", "title": "Victoria Park Ave At Conroy Ave", "lat": "43.7015099"}, {"stopId": "8462", "lon": "-79.29355", "tag": "5154", "title": "Victoria Park Ave At St Bedes Rd", "lat": "43.70338"}, {"stopId": "8484", "lon": "-79.29442", "tag": "1745", "title": "Victoria Park Ave At Meighen Ave", "lat": "43.7053599"}, {"stopId": "8446", "lon": "-79.2949", "tag": "7793", "title": "Victoria Park Ave At Dawes Rd", "lat": "43.70661"}, {"stopId": "8505", "lon": "-79.29577", "tag": "1616", "title": "Victoria Park Ave At St Clair Ave East", "lat": "43.70862"}, {"stopId": "8506", "lon": "-79.29659", "tag": "5841", "title": "Victoria Park Ave At Stamford Sq", "lat": "43.7105999"}, {"stopId": "8434", "lon": "-79.29791", "tag": "3445", "title": "Victoria Park Ave At Bassett Ave", "lat": "43.7137"}, {"stopId": "8430", "lon": "-79.29851", "tag": "1423", "title": "Victoria Park Ave At Amsterdam Ave", "lat": "43.71514"}, {"stopId": "8451", "lon": "-79.2995099", "tag": "7334", "title": "Victoria Park Ave At Edge Park Ave", "lat": "43.7175199"}, {"stopId": "8519", "lon": "-79.29997", "tag": "8529", "title": "Victoria Park Ave At Valdane Dr", "lat": "43.7186"}, {"stopId": "8502", "lon": "-79.30088", "tag": "6568", "title": "Victoria Park Ave At Southmead Rd", "lat": "43.72069"}, {"stopId": "8455", "lon": "-79.3017099", "tag": "5680", "title": "Victoria Park Ave At Eglinton Sq", "lat": "43.7227699"}, {"stopId": "6153", "lon": "-79.30224", "tag": "8181", "title": "Victoria Park Ave At Eglinton Ave East", "lat": "43.7241"}, {"stopId": "6152", "lon": "-79.30276", "tag": "10271", "title": "Victoria Park Ave At Eglinton Ave East North Side", "lat": "43.7253699"}, {"stopId": "8442", "lon": "-79.30328", "tag": "868", "title": "Victoria Park Ave At Craigton Dr", "lat": "43.72655"}, {"stopId": "8435", "lon": "-79.30447", "tag": "6608", "title": "Victoria Park Ave At Biscayne Blvd North Side", "lat": "43.7294299"}, {"stopId": "8431", "lon": "-79.30555", "tag": "3155", "title": "Victoria Park Ave At Arncliffe Cres North Side", "lat": "43.73212"}, {"stopId": "8470", "lon": "-79.3065399", "tag": "10128", "title": "Victoria Park Ave At Innismore Cres", "lat": "43.7345599"}, {"stopId": "8512", "lon": "-79.3074", "tag": "6460", "title": "Victoria Park Ave At Surrey Ave North Side", "lat": "43.73662"}, {"stopId": "8499", "lon": "-79.3082", "tag": "1174", "title": "Victoria Park Ave At Sloane Ave", "lat": "43.73852"}, {"stopId": "8474", "lon": "-79.30916", "tag": "3003", "title": "Victoria Park Ave At Janet Blvd", "lat": "43.7408499"}, {"stopId": "8475", "lon": "-79.30952", "tag": "8992", "title": "Victoria Park Ave At Lawrence Ave East", "lat": "43.74176"}, {"stopId": "8449", "lon": "-79.31065", "tag": "2461", "title": "Victoria Park Ave At Deanvar Ave", "lat": "43.7448999"}, {"stopId": "8466", "lon": "-79.31184", "tag": "9286", "title": "Victoria Park Ave At Greylawn Cres (South)", "lat": "43.74846"}, {"stopId": "14271", "lon": "-79.3128699", "tag": "8883", "title": "Victoria Park Ave At Rowena Dr", "lat": "43.7513999"}, {"stopId": "8473", "lon": "-79.31333", "tag": "5429", "title": "Victoria Park Ave At Ivordale Cres (South)", "lat": "43.75276"}, {"stopId": "8437", "lon": "-79.3138599", "tag": "7172", "title": "Victoria Park Ave At Cassandra Blvd", "lat": "43.7542599"}, {"stopId": "8471", "lon": "-79.3143299", "tag": "10083", "title": "Victoria Park Ave At Ivordale Cres (North)", "lat": "43.7555699"}, {"stopId": "8456", "lon": "-79.31521", "tag": "10377", "title": "Victoria Park Ave At Ellesmere Rd North Side", "lat": "43.7582399"}, {"stopId": "7417", "lon": "-79.31611", "tag": "3238", "title": "Victoria Park Ave At Paget Rd North Side", "lat": "43.76019"}, {"stopId": "7416", "lon": "-79.31716", "tag": "5603", "title": "Victoria Park Ave At Pachino Blvd North Side", "lat": "43.76253"}, {"stopId": "7429", "lon": "-79.31796", "tag": "2334", "title": "Victoria Park Ave At Terraview Blvd", "lat": "43.7644499"}, {"stopId": "6324", "lon": "-79.3223", "tag": "8037", "title": "Consumers Rd At Victoria Park Ave West Side", "lat": "43.7718799"}, {"stopId": "6323", "lon": "-79.3269199", "tag": "4652", "title": "422 Consumers Rd", "lat": "43.7707999"}, {"stopId": "6321", "lon": "-79.3301499", "tag": "1835", "title": "250 Consumers Rd", "lat": "43.7705699"}, {"stopId": "10252", "lon": "-79.3319799", "tag": "4036", "title": "Yorkland Blvd (South) At Consumers Rd West Side", "lat": "43.7711599"}, {"stopId": "10253", "lon": "-79.33516", "tag": "6262", "title": "180 Yorkland Blvd", "lat": "43.77116"}, {"stopId": "9515", "lon": "-79.33575", "tag": "9802", "title": "Yorkland Blvd (North) At Yorkland Rd East Side", "lat": "43.7729599"}, {"stopId": "9516", "lon": "-79.3339099", "tag": "6861", "title": "280 Yorkland Blvd (North)", "lat": "43.77336"}, {"stopId": "9517", "lon": "-79.3325", "tag": "6006", "title": "Yorkland Blvd (North) At Consumers Rd", "lat": "43.77367"}, {"stopId": "7161", "lon": "-79.33171", "tag": "2901", "title": "Sheppard Ave East At Brian Dr West Side", "lat": "43.7752999"}, {"stopId": "7191", "lon": "-79.3357499", "tag": "2857", "title": "1900 Sheppard Ave East", "lat": "43.7757499"}, {"stopId": "7226", "lon": "-79.3451599", "tag": "5856", "title": "Sheppard Ave East At Parkway Forest Dr West Side", "lat": "43.77563"}, {"lon": "-79.34524", "tag": "14150_ar", "title": "Don Mills Station", "lat": "43.7757999"}, {"stopId": "14976", "lon": "-79.28925", "tag": "14734", "title": "Victoria Park Station", "lat": "43.6944099"}, {"stopId": "8481", "lon": "-79.32125", "tag": "7722", "title": "Victoria Park Ave At Meadowacres Dr", "lat": "43.7718"}, {"stopId": "7412", "lon": "-79.32196", "tag": "6705", "title": "Victoria Park Ave At Esquire Rd", "lat": "43.7734199"}, {"stopId": "8497", "lon": "-79.32272", "tag": "9608", "title": "Victoria Park Ave At Sheppard Ave East", "lat": "43.77508"}, {"stopId": "7419", "lon": "-79.32415", "tag": "4579", "title": "Victoria Park Ave At Patrick Blvd North Side", "lat": "43.7780599"}, {"stopId": "8469", "lon": "-79.3252199", "tag": "2560", "title": "Victoria Park Ave At Huntingwood Dr", "lat": "43.7802399"}, {"stopId": "8426", "lon": "-79.32626", "tag": "8659", "title": "2793 Victoria Park Ave", "lat": "43.78242"}, {"stopId": "8428", "lon": "-79.32719", "tag": "9041", "title": "Victoria Park Ave At Altair Ave North Side", "lat": "43.78448"}, {"stopId": "8494", "lon": "-79.32791", "tag": "6545", "title": "Victoria Park Ave At Pleasant View Dr North Side", "lat": "43.7859899"}, {"stopId": "8459", "lon": "-79.3294099", "tag": "1970", "title": "Victoria Park Ave At Ferncrest Gate", "lat": "43.7891799"}, {"stopId": "8460", "lon": "-79.3311299", "tag": "3056", "title": "Victoria Park Ave At Finch Ave East", "lat": "43.7929299"}, {"stopId": "8467", "lon": "-79.33258", "tag": "3332", "title": "Victoria Park Ave At Hare Gate", "lat": "43.7960399"}, {"stopId": "8485", "lon": "-79.33342", "tag": "6627", "title": "Victoria Park Ave At Morecambe Gate", "lat": "43.79797"}, {"stopId": "8486", "lon": "-79.33456", "tag": "6641", "title": "Victoria Park Ave At Navaho Dr", "lat": "43.80046"}, {"stopId": "8480", "lon": "-79.3360699", "tag": "8809", "title": "Victoria Park Ave At McNicoll Ave", "lat": "43.8038999"}, {"stopId": "3159", "lon": "-79.33702", "tag": "4319", "title": "Victoria Park Ave At Tempo Ave", "lat": "43.8059899"}, {"stopId": "3156", "lon": "-79.33813", "tag": "7127", "title": "Victoria Park Ave At Sparks Ave", "lat": "43.80844"}, {"stopId": "8464", "lon": "-79.33892", "tag": "3664", "title": "Victoria Park Ave At Gordon Baker Rd", "lat": "43.8103"}, {"stopId": "9522", "lon": "-79.34023", "tag": "5359", "title": "Opposite 4000 Victoria Park Ave", "lat": "43.81352"}, {"stopId": "8511", "lon": "-79.3410099", "tag": "5826", "title": "Victoria Park Ave At Steeles Ave East", "lat": "43.8153099"}, {"lon": "-79.34141", "tag": "1680_ar", "title": "Victoria Park Ave Loop At Steeles Ave East", "lat": "43.8166199"}, {"stopId": "4689", "lon": "-79.28818", "tag": "2450", "title": "Victoria Park Ave At Danforth Ave", "lat": "43.6910799"}, {"stopId": "11348", "lon": "-79.2887699", "tag": "5105", "title": "Victoria Park Ave At Denton Ave", "lat": "43.6926299"}, {"stopId": "11376", "lon": "-79.28937", "tag": "4288", "title": "Victoria Park Ave At Victoria Park Station", "lat": "43.6942099"}], "tag": "24", "latMin": "43.6910799", "title": "24-Victoria Park", "latMax": "43.8166199", "lonMin": "-79.34524", "direction": [{"stop": [{"tag": "14733"}, {"tag": "4384"}, {"tag": "6679"}, {"tag": "5154"}, {"tag": "1745"}, {"tag": "7793"}, {"tag": "1616"}, {"tag": "5841"}, {"tag": "3445"}, {"tag": "1423"}, {"tag": "7334"}, {"tag": "8529"}, {"tag": "6568"}, {"tag": "5680"}, {"tag": "8181"}, {"tag": "10271"}, {"tag": "868"}, {"tag": "6608"}, {"tag": "3155"}, {"tag": "10128"}, {"tag": "6460"}, {"tag": "1174"}, {"tag": "3003"}, {"tag": "8992"}, {"tag": "2461"}, {"tag": "9286"}, {"tag": "8883"}, {"tag": "5429"}, {"tag": "7172"}, {"tag": "10083"}, {"tag": "10377"}, {"tag": "3238"}, {"tag": "5603"}, {"tag": "2334"}, {"tag": "8037"}, {"tag": "4652"}, {"tag": "1835"}, {"tag": "4036"}, {"tag": "6262"}, {"tag": "9802"}, {"tag": "6861"}, {"tag": "6006"}, {"tag": "2901"}, {"tag": "2857"}, {"tag": "5856"}, {"tag": "14150_ar"}], "name": "North", "useForUI": "true", "tag": "24_1_24B", "title": "North - 24b Victoria Park towards Don Mills Station via Consumers Rd", "branch": "24B"}, {"stop": [{"tag": "14150"}, {"tag": "5480"}, {"tag": "4699"}, {"tag": "6700"}, {"tag": "10234"}, {"tag": "2941"}, {"tag": "3439"}, {"tag": "7789"}, {"tag": "3984"}, {"tag": "6666"}, {"tag": "8828"}, {"tag": "5137"}, {"tag": "2288"}, {"tag": "9946"}, {"tag": "4218"}, {"tag": "10088"}, {"tag": "7892"}, {"tag": "8530"}, {"tag": "8006"}, {"tag": "1986"}, {"tag": "8310"}, {"tag": "1453"}, {"tag": "1401"}, {"tag": "749"}, {"tag": "6829"}, {"tag": "2717"}, {"tag": "1803"}, {"tag": "1781"}, {"tag": "3970"}, {"tag": "9280"}, {"tag": "2096"}, {"tag": "25094"}, {"tag": "6820"}, {"tag": "2517"}, {"tag": "8750"}, {"tag": "4046"}, {"tag": "7449"}, {"tag": "9831"}, {"tag": "6315"}, {"tag": "9165"}, {"tag": "5235"}, {"tag": "24789"}, {"tag": "14797"}, {"tag": "14733_ar"}], "name": "South", "useForUI": "true", "tag": "24_0_24B", "title": "South - 24b Victoria Park towards Victoria Park Station via Consumers Rd", "branch": "24B"}, {"stop": [{"tag": "2450"}, {"tag": "5105"}, {"tag": "4288"}, {"tag": "4384"}, {"tag": "6679"}, {"tag": "5154"}, {"tag": "1745"}, {"tag": "7793"}, {"tag": "1616"}, {"tag": "5841"}, {"tag": "3445"}, {"tag": "1423"}, {"tag": "7334"}, {"tag": "8529"}, {"tag": "6568"}, {"tag": "5680"}, {"tag": "8181"}, {"tag": "10271"}, {"tag": "868"}, {"tag": "6608"}, {"tag": "3155"}, {"tag": "10128"}, {"tag": "6460"}, {"tag": "1174"}, {"tag": "3003"}, {"tag": "8992"}, {"tag": "2461"}, {"tag": "9286"}, {"tag": "8883"}, {"tag": "5429"}, {"tag": "7172"}, {"tag": "10083"}, {"tag": "10377"}, {"tag": "3238"}, {"tag": "5603"}, {"tag": "2334"}, {"tag": "7722"}, {"tag": "6705"}, {"tag": "9608"}, {"tag": "4579"}, {"tag": "2560"}, {"tag": "8659"}, {"tag": "9041"}, {"tag": "6545"}, {"tag": "1970"}, {"tag": "3056"}, {"tag": "3332"}, {"tag": "6627"}, {"tag": "6641"}, {"tag": "8809"}, {"tag": "4319"}, {"tag": "7127"}, {"tag": "3664"}, {"tag": "5359"}, {"tag": "5826"}, {"tag": "1680_ar"}], "name": "North", "useForUI": "true", "tag": "24_1_da24A", "title": "North - 24a Victoria Park towards Steeles", "branch": "24A"}, {"stop": [{"tag": "1680"}, {"tag": "3956"}, {"tag": "6055"}, {"tag": "3149"}, {"tag": "7009"}, {"tag": "7592"}, {"tag": "2326"}, {"tag": "2609"}, {"tag": "3931"}, {"tag": "9293"}, {"tag": "1194"}, {"tag": "4878"}, {"tag": "5515"}, {"tag": "9737"}, {"tag": "2670"}, {"tag": "3660"}, {"tag": "1487"}, {"tag": "6220"}, {"tag": "4225"}, {"tag": "7615"}, {"tag": "9920"}, {"tag": "3012"}, {"tag": "2288"}, {"tag": "9946"}, {"tag": "4218"}, {"tag": "10088"}, {"tag": "7892"}, {"tag": "8530"}, {"tag": "8006"}, {"tag": "1986"}, {"tag": "8310"}, {"tag": "1453"}, {"tag": "1401"}, {"tag": "749"}, {"tag": "6829"}, {"tag": "2717"}, {"tag": "1803"}, {"tag": "1781"}, {"tag": "3970"}, {"tag": "9280"}, {"tag": "2096"}, {"tag": "25094"}, {"tag": "6820"}, {"tag": "2517"}, {"tag": "8750"}, {"tag": "4046"}, {"tag": "7449"}, {"tag": "9831"}, {"tag": "6315"}, {"tag": "9165"}, {"tag": "5235"}, {"tag": "24789"}, {"tag": "14797"}, {"tag": "14700"}, {"tag": "14731"}, {"tag": "8504"}], "name": "South", "useForUI": "true", "tag": "24_0_24Ada", "title": "South - 24 Victoria Park towards Danforth", "branch": "24"}]}}